Workbook

Sheet Estudiantes
A1: ID | B1: Nombre | C1: Apellido | D1: email | E1: Grado | F1: Plan / Jornada | G1: Mensualidad Base | H1: Recargo < 2 años | I1: Libro (Único) | J1: Total Mensual | K1: Total Mes
A2: 1 | B2: Mateo | C2: García | D2: aelabs70@gmail.com | E2: Caminadores | F2: Media Jornada | G2: 209 | H2: 55 | I2: 0 | J2: 264 | K2: =G2+H2 -> 264
A3: 2 | B3: Elena | C3: Rodríguez | D3: aelabs70@gmail.com | E3: Jardín | F3: Tiempo Completo | G3: 626 | H3: 0 | I3: 40 | J3: 626 | K3: =G3+H3 -> 626
A4: 3 | B4: Lucas | C4: Martínez | D4: aelabs70@gmail.com | E4: Prejardín | F4: Media + Almuerzo | G4: 354 | H4: 0 | I4: 40 | J4: 354 | K4: =G4+H4 -> 354
A5: 4 | B5: Sofía | C5: López | D5: aelabs70@gmail.com | E5: Párvulos | F5: Media + Lonchera | G5: 305 | H5: 55 | I5: 0 | J5: 360 | K5: =G5+H5 -> 360
A6: 5 | B6: Diego | C6: Sánchez | D6: aelabs70@gmail.com | E6: Transición | F6: Tiempo Completo | G6: 626 | H6: 0 | I6: 40 | J6: 626 | K6: =G6+H6 -> 626
A7: 6 | B7: Valentina | C7: Pérez | D7: aelabs70@gmail.com | E7: Caminadores | F7: Media + Desayuno | G7: 361 | H7: 55 | I7: 0 | J7: 416 | K7: =G7+H7 -> 416
A8: 7 | B8: Thiago | C8: Gómez | D8: aelabs70@gmail.com | E8: Jardín | F8: Media + Almuerzo/Lonchera | G8: 390 | H8: 0 | I8: 40 | J8: 390 | K8: =G8+H8 -> 390
A9: 8 | B9: Isabella | C9: Ruiz | D9: aelabs70@gmail.com | E9: Párvulos | F9: Media Jornada | G9: 209 | H9: 55 | I9: 0 | J9: 264 | K9: =G9+H9 -> 264
A10: 9 | B10: Samuel | C10: Castro | D10: aelabs70@gmail.com | E10: Prejardín | F10: Media + Desayuno/Almuerzo | G10: 471 | H10: 0 | I10: 40 | J10: 471 | K10: =G10+H10 -> 471
A11: 10 | B11: Emma | C11: Morales | D11: aelabs70@gmail.com | E11: Transición | F11: Media Jornada | G11: 209 | H11: 0 | I11: 40 | J11: 209 | K11: =G11+H11 -> 209
A12: 11 | B12: Joaquín | C12: Ortiz | D12: aelabs70@gmail.com | E12: Caminadores | F12: Tiempo Completo | G12: 626 | H12: 55 | I12: 0 | J12: 681 | K12: =G12+H12 -> 681
A13: 12 | B13: Mia | C13: Silva | D13: aelabs70@gmail.com | E13: Jardín | F13: Media + Lonchera | G13: 305 | H13: 0 | I13: 40 | J13: 305 | K13: =G13+H13 -> 305
... A23: 22 | B23: Emilia | C23: Soto | D23: aelabs70@gmail.com | E23: Jardín | F23: Media Jornada | G23: 209 | H23: 0 | I23: 40 | J23: 209 | K23: =G23+H23 -> 209

Sheet Pagos
A1: Fecha | B1: ID Estudiante | C1: Nombre Niño | D1: Concepto | E1: Valor Pagado | F1: Forma de Pago
A2: 45659 | B2: 1 | C2: Mateo García | D2: Matrícula 2025 | E2: 471.15 | F2: Transferencia
A3: 45659 | B3: 2 | C3: Elena Rodríguez | D3: Abono Matrícula | E3: 250 | F3: Efectivo
A4: 45660 | B4: 3 | C4: Lucas Martínez | D4: Matrícula + Libro | E4: 511.15 | F4: Transferencia
A5: 45661 | B5: 4 | C5: Sofía López | D5: Matrícula 2025 | E5: 471.15 | F5: Nequi
A6: 45662 | B6: 2 | C6: Elena Rodríguez | D6: Saldo Matrícula | E6: 221.15 | F6: Transferencia
A7: 45662 | B7: 2 | C7: Elena Rodríguez | D7: Pago Libro Jardín | E7: 40 | F7: Transferencia
A8: 45689 | B8: 1 | C8: Mateo García | D8: Pensión Febrero | E8: 264 | F8: Transferencia
A9: 45690 | B9: 5 | C9: Diego Sánchez | D9: Pensión Febrero | E9: 626 | F9: Nequi
A10: 45691 | B10: 4 | C10: Sofía López | D10: Abono Pensión Feb | E10: 200 | F10: Efectivo
A11: 45693 | B11: 6 | C11: Valentina Pérez | D11: Pensión Febrero | E11: 416 | F11: Transferencia
A12: 45694 | B12: 4 | C12: Sofía López | D12: Saldo Pensión Feb | E12: 160 | F12: Efectivo
A13: 45695 | B13: 7 | C13: Thiago Gómez | D13: Pensión Febrero | E13: 390 | F13: Nequi
... A24: 45725 | B24: 1 | C24: Mateo García | D24: Pensión Marzo | E24: 264 | F24: Transferencia

Sheet Estados de cuenta
A1: RC | B1: Estudiante | C1: Celular | D1: Total Deuda (Matrícula + 3 Meses) | E1: Total Pagado | F1: Saldo Pendiente | G1: Estado
A2: 1 | B2: =VLOOKUP(A2, Estudiantes!A:B, 2, FALSE) -> Mateo | C2: 573193275591 | D2: {=(471.15 + INDEX(Estudiantes!$J:$J, MATCH(A2, Estudiantes!$A:$A, 0))) + (INDEX(Estudiantes!$K:$K, MATCH(A2, Estudiantes!$A:$A, 0)) * 2)} -> 1263.15 | E2: =SUMIF(Pagos!$B:$B, A2, Pagos!$E:$E) -> 1263.15 | F2: =D2-E2 -> 0 | G2: =IF(F2 > 0, "Mora", "Al día") -> Al día
A3: 2 | B3: =VLOOKUP(A3, Estudiantes!A:B, 2, FALSE) -> Elena | C3: 573193275591 | D3: {=(471.15 + INDEX(Estudiantes!$J:$J, MATCH(A3, Estudiantes!$A:$A, 0))) + (INDEX(Estudiantes!$K:$K, MATCH(A3, Estudiantes!$A:$A, 0)) * 2)} -> 2349.15 | E3: =SUMIF(Pagos!$B:$B, A3, Pagos!$E:$E) -> 511.15 | F3: =D3-E3 -> 1838 | G3: =IF(F3 > 0, "Mora", "Al día") -> Mora
A4: 3 | B4: =VLOOKUP(A4, Estudiantes!A:B, 2, FALSE) -> Lucas | C4: 573193275591 | D4: {=(471.15 + INDEX(Estudiantes!$J:$J, MATCH(A4, Estudiantes!$A:$A, 0))) + (INDEX(Estudiantes!$K:$K, MATCH(A4, Estudiantes!$A:$A, 0)) * 2)} -> 1533.15 | E4: =SUMIF(Pagos!$B:$B, A4, Pagos!$E:$E) -> 511.15 | F4: =D4-E4 -> 1022 | G4: =IF(F4 > 0, "Mora", "Al día") -> Mora
A5: 4 | B5: =VLOOKUP(A5, Estudiantes!A:B, 2, FALSE) -> Sofía | C5: 573193275591 | D5: {=(471.15 + INDEX(Estudiantes!$J:$J, MATCH(A5, Estudiantes!$A:$A, 0))) + (INDEX(Estudiantes!$K:$K, MATCH(A5, Estudiantes!$A:$A, 0)) * 2)} -> 1551.15 | E5: =SUMIF(Pagos!$B:$B, A5, Pagos!$E:$E) -> 831.15 | F5: =D5-E5 -> 720 | G5: =IF(F5 > 0, "Mora", "Al día") -> Mora
A6: 5 | B6: =VLOOKUP(A6, Estudiantes!A:B, 2, FALSE) -> Diego | C6: 573193275591 | D6: {=(471.15 + INDEX(Estudiantes!$J:$J, MATCH(A6, Estudiantes!$A:$A, 0))) + (INDEX(Estudiantes!$K:$K, MATCH(A6, Estudiantes!$A:$A, 0)) * 2)} -> 2349.15 | E6: =SUMIF(Pagos!$B:$B, A6, Pagos!$E:$E) -> 626 | F6: =D6-E6 -> 1723.15 | G6: =IF(F6 > 0, "Mora", "Al día") -> Mora
A7: 6 | B7: =VLOOKUP(A7, Estudiantes!A:B, 2, FALSE) -> Valentina | C7: 573193275591 | D7: {=(471.15 + INDEX(Estudiantes!$J:$J, MATCH(A7, Estudiantes!$A:$A, 0))) + (INDEX(Estudiantes!$K:$K, MATCH(A7, Estudiantes!$A:$A, 0)) * 2)} -> 1719.15 | E7: =SUMIF(Pagos!$B:$B, A7, Pagos!$E:$E) -> 416 | F7: =D7-E7 -> 1303.15 | G7: =IF(F7 > 0, "Mora", "Al día") -> Mora
A8: 7 | B8: =VLOOKUP(A8, Estudiantes!A:B, 2, FALSE) -> Thiago | C8: 573193275591 | D8: {=(471.15 + INDEX(Estudiantes!$J:$J, MATCH(A8, Estudiantes!$A:$A, 0))) + (INDEX(Estudiantes!$K:$K, MATCH(A8, Estudiantes!$A:$A, 0)) * 2)} -> 1641.15 | E8: =SUMIF(Pagos!$B:$B, A8, Pagos!$E:$E) -> 390 | F8: =D8-E8 -> 1251.15 | G8: =IF(F8 > 0, "Mora", "Al día") -> Mora
A9: 8 | B9: =VLOOKUP(A9, Estudiantes!A:B, 2, FALSE) -> Isabella | C9: 573193275591 | D9: {=(471.15 + INDEX(Estudiantes!$J:$J, MATCH(A9, Estudiantes!$A:$A, 0))) + (INDEX(Estudiantes!$K:$K, MATCH(A9, Estudiantes!$A:$A, 0)) * 2)} -> 1263.15 | E9: =SUMIF(Pagos!$B:$B, A9, Pagos!$E:$E) -> 264 | F9: =D9-E9 -> 999.15 | G9: =IF(F9 > 0, "Mora", "Al día") -> Mora
A10: 9 | B10: =VLOOKUP(A10, Estudiantes!A:B, 2, FALSE) -> Samuel | C10: 573193275591 | D10: {=(471.15 + INDEX(Estudiantes!$J:$J, MATCH(A10, Estudiantes!$A:$A, 0))) + (INDEX(Estudiantes!$K:$K, MATCH(A10, Estudiantes!$A:$A, 0)) * 2)} -> 1884.15 | E10: =SUMIF(Pagos!$B:$B, A10, Pagos!$E:$E) -> 471 | F10: =D10-E10 -> 1413.15 | G10: =IF(F10 > 0, "Mora", "Al día") -> Mora
A11: 10 | B11: =VLOOKUP(A11, Estudiantes!A:B, 2, FALSE) -> Emma | C11: 573193275591 | D11: {=(471.15 + INDEX(Estudiantes!$J:$J, MATCH(A11, Estudiantes!$A:$A, 0))) + (INDEX(Estudiantes!$K:$K, MATCH(A11, Estudiantes!$A:$A, 0)) * 2)} -> 1098.15 | E11: =SUMIF(Pagos!$B:$B, A11, Pagos!$E:$E) -> 209 | F11: =D11-E11 -> 889.15 | G11: =IF(F11 > 0, "Mora", "Al día") -> Mora
A12: 11 | B12: =VLOOKUP(A12, Estudiantes!A:B, 2, FALSE) -> Joaquín | C12: 573193275591 | D12: {=(471.15 + INDEX(Estudiantes!$J:$J, MATCH(A12, Estudiantes!$A:$A, 0))) + (INDEX(Estudiantes!$K:$K, MATCH(A12, Estudiantes!$A:$A, 0)) * 2)} -> 2514.15 | E12: =SUMIF(Pagos!$B:$B, A12, Pagos!$E:$E) -> 681 | F12: =D12-E12 -> 1833.15 | G12: =IF(F12 > 0, "Mora", "Al día") -> Mora
A13: 12 | B13: =VLOOKUP(A13, Estudiantes!A:B, 2, FALSE) -> Mia | C13: 573193275591 | D13: {=(471.15 + INDEX(Estudiantes!$J:$J, MATCH(A13, Estudiantes!$A:$A, 0))) + (INDEX(Estudiantes!$K:$K, MATCH(A13, Estudiantes!$A:$A, 0)) * 2)} -> 1386.15 | E13: =SUMIF(Pagos!$B:$B, A13, Pagos!$E:$E) -> 305 | F13: =D13-E13 -> 1081.15 | G13: =IF(F13 > 0, "Mora", "Al día") -> Mora
... A23: 22 | B23: =VLOOKUP(A23, Estudiantes!A:B, 2, FALSE) -> Emilia | C23: 573193275591 | D23: {=(471.15 + INDEX(Estudiantes!$J:$J, MATCH(A23, Estudiantes!$A:$A, 0))) + (INDEX(Estudiantes!$K:$K, MATCH(A23, Estudiantes!$A:$A, 0)) * 2)} -> 1098.15 | E23: =SUMIF(Pagos!$B:$B, A23, Pagos!$E:$E) -> 0 | F23: =D23-E23 -> 1098.15 | G23: =IF(F23 > 0, "Mora", "Al día") -> Mora
